hobohm.py
hobohm-2.0.2.dist-info/LICENSE
hobohm-2.0.2.dist-info/METADATA
hobohm-2.0.2.dist-info/WHEEL
hobohm-2.0.2.dist-info/entry_points.txt
hobohm-2.0.2.dist-info/top_level.txt
hobohm-2.0.2.dist-info/RECORD
