Metadata-Version: 2.1
Name: hobohm
Version: 2.0.2
Summary: [DEPRECATED] Select non-redundant subset of DNA or protein-sequences
Home-page: https://github.com/agormp/hobohm
Author: Anders Gorm Pedersen
Author-email: agpe@dtu.dk
Classifier: Programming Language :: Python :: 3
Classifier: License :: OSI Approved :: GNU General Public License v3 (GPLv3)
Classifier: Operating System :: OS Independent
Requires-Python: >=3.6
License-File: LICENSE
Requires-Dist: pandas
